inclusion/__init__.py
inclusion/cli.py
inclusion/scanner.py
inclusion-1.0.2.dist-info/LICENSE
inclusion-1.0.2.dist-info/METADATA
inclusion-1.0.2.dist-info/WHEEL
inclusion-1.0.2.dist-info/entry_points.txt
inclusion-1.0.2.dist-info/top_level.txt
inclusion-1.0.2.dist-info/RECORD
