Metadata-Version: 2.1
Name: inclusion
Version: 1.0.2
Summary: A tool to check for file inclusion vulnerabilities.
Home-page: https://github.com/ByteBreach/inclusion
Author: MrFidal
Author-email: mrfidal@proton.me
Classifier: Programming Language :: Python :: 3
Classifier: License :: OSI Approved :: MIT License
License-File: LICENSE
Requires-Dist: requests
